workflow/__init__.py
workflow/manager/__init__.py
workflow/manager/actionmanager.py
workflow/manager/configure.zcml
workflow/manager/dependencies.zcml
workflow/manager/interfaces.py
workflow/manager/permissions.py
workflow/manager/permissions.zcml
workflow/manager/profiles.zcml
workflow/manager/utils.py
workflow/manager/api/__init__.py
workflow/manager/api/configure.zcml
workflow/manager/api/services/__init__.py
workflow/manager/api/services/configure.zcml
workflow/manager/api/services/workflow/__init__.py
workflow/manager/api/services/workflow/base.py
workflow/manager/api/services/workflow/configure.zcml
workflow/manager/api/services/workflow/layout.py
workflow/manager/api/services/workflow/state.py
workflow/manager/api/services/workflow/transition.py
workflow/manager/api/services/workflow/workflow.py
workflow/manager/browser/configure.zcml
workflow/manager/content/__init__.py
workflow/manager/controlpanel/__init__.py
workflow/manager/controlpanel/configure.zcml
workflow/manager/controlpanel/control_panel/__init__.py
workflow/manager/controlpanel/control_panel/configure.zcml
workflow/manager/controlpanel/control_panel/controlpanel.py
workflow/manager/indexers/__init__.py
workflow/manager/indexers/configure.zcml
workflow/manager/locales/__init__.py
workflow/manager/locales/__main__.py
workflow/manager/locales/workflow.manager.pot
workflow/manager/locales/en/LC_MESSAGES/workflow.manager.mo
workflow/manager/locales/en/LC_MESSAGES/workflow.manager.po
workflow/manager/profiles/default/browserlayer.xml
workflow/manager/profiles/default/catalog.xml
workflow/manager/profiles/default/controlpanel.xml
workflow/manager/profiles/default/diff_tool.xml
workflow/manager/profiles/default/metadata.xml
workflow/manager/profiles/default/repositorytool.xml
workflow/manager/profiles/default/rolemap.xml
workflow/manager/profiles/default/theme.xml
workflow/manager/profiles/default/types.xml
workflow/manager/profiles/default/registry/control_panel.xml
volto_workflow_manager-1.0.0a0.dist-info/METADATA
volto_workflow_manager-1.0.0a0.dist-info/WHEEL
volto_workflow_manager-1.0.0a0.dist-info/entry_points.txt
volto_workflow_manager-1.0.0a0.dist-info/licenses/LICENSE.GPL
volto_workflow_manager-1.0.0a0.dist-info/licenses/LICENSE.md
volto_workflow_manager-1.0.0a0.dist-info/RECORD
