Metadata-Version: 2.4
Name: volto-workflow-manager
Version: 1.0.0a0
Summary: A new project using Plone 6.
Project-URL: Homepage, https://github.com/collective/workflow-manager
Project-URL: PyPI, https://pypi.org/project/workflow.manager
Project-URL: Source, https://github.com/collective/workflow-manager
Project-URL: Tracker, https://github.com/collective/workflow-manager/issues
Author-email: Plone Foundation <collective@plone.org>
License-Expression: GPL-2.0-only
License-File: LICENSE.GPL
License-File: LICENSE.md
Keywords: CMS,Plone,Python
Classifier: Development Status :: 3 - Alpha
Classifier: Environment :: Web Environment
Classifier: Framework :: Plone
Classifier: Framework :: Plone :: 6.1
Classifier: Framework :: Plone :: Addon
Classifier: License :: OSI Approved :: GNU General Public License v2 (GPLv2)
Classifier: Operating System :: OS Independent
Classifier: Programming Language :: Python
Classifier: Programming Language :: Python :: 3.12
Requires-Python: >=3.12
Requires-Dist: plone-api
Requires-Dist: plone-restapi
Requires-Dist: plone-volto
Requires-Dist: products-cmfplone==6.1.1
Provides-Extra: test
Requires-Dist: horse-with-no-namespace; extra == 'test'
Requires-Dist: plone-app-testing; extra == 'test'
Requires-Dist: plone-restapi[test]; extra == 'test'
Requires-Dist: pytest; extra == 'test'
Requires-Dist: pytest-cov; extra == 'test'
Requires-Dist: pytest-plone>=0.5.0; extra == 'test'
